<?xml version="1.0" encoding="UTF-8" ?>
<!--
  備金確定日変更 (siBknKktymdHenkou) 画面項目定義
-->
<kinouDef>
  <kinouId>sibknkktymdhenkou</kinouId>
  <TFieldDefs>

    <TFieldDef>
      <pageNo>1</pageNo>
      <id>headerButtons</id>
      <groupType>buttons</groupType>
      <columnCount>0</columnCount>
      <labelStyle></labelStyle>
      <outerStyle></outerStyle>
      <innerStyle>rightButtons</innerStyle>
      <inputMethod></inputMethod>
      <fieldType>NOLABELOUTPUT</fieldType>
      <required>false</required>
      <unit></unit>
      <prefix></prefix>
      <suffix></suffix>
      <param></param>
      <dataSource></dataSource>
    </TFieldDef>
    <TFieldDef>
      <pageNo>1</pageNo>
      <id>headerButtons:tojiruBtn</id>
      <format></format>
      <groupType></groupType>
      <columnCount>0</columnCount>
      <labelStyle></labelStyle>
      <outerStyle></outerStyle>
      <innerStyle></innerStyle>
      <inputMethod>closeButton</inputMethod>
      <fieldType>INPUT</fieldType>
      <required>false</required>
      <unit></unit>
      <prefix></prefix>
      <suffix></suffix>
      <param></param>
      <dataSource></dataSource>
    </TFieldDef>
    <TFieldDef>
      <pageNo>1</pageNo>
      <id>kihonInfo</id>
      <groupType>group</groupType>
      <columnCount>1</columnCount>
      <labelStyle></labelStyle>
      <outerStyle></outerStyle>
      <innerStyle></innerStyle>
      <inputMethod></inputMethod>
      <fieldType>NOLABELOUTPUT</fieldType>
      <required>false</required>
      <unit></unit>
      <prefix></prefix>
      <suffix></suffix>
      <param></param>
      <dataSource></dataSource>
    </TFieldDef>
    <TFieldDef>
      <pageNo>1</pageNo>
      <id>kihonInfo:syono</id>
      <format></format>
      <groupType></groupType>
      <columnCount>1</columnCount>
      <labelStyle></labelStyle>
      <outerStyle>c1</outerStyle>
      <innerStyle></innerStyle>
      <inputMethod>text</inputMethod>
      <fieldType>INPUT</fieldType>
      <required>true</required>
      <unit></unit>
      <prefix></prefix>
      <suffix></suffix>
      <param></param>
      <dataSource></dataSource>
    </TFieldDef>
    <TFieldDef>
      <pageNo>1</pageNo>
      <id>footerButtons</id>
      <groupType>buttons</groupType>
      <columnCount>1</columnCount>
      <labelStyle></labelStyle>
      <outerStyle></outerStyle>
      <innerStyle></innerStyle>
      <inputMethod></inputMethod>
      <fieldType>NOLABELOUTPUT</fieldType>
      <required>false</required>
      <unit></unit>
      <prefix></prefix>
      <suffix></suffix>
      <param></param>
      <dataSource></dataSource>
    </TFieldDef>
    <TFieldDef>
      <pageNo>1</pageNo>
      <id>footerButtons:ketteiBtn</id>
      <format></format>
      <groupType></groupType>
      <columnCount>1</columnCount>
      <labelStyle></labelStyle>
      <outerStyle></outerStyle>
      <innerStyle></innerStyle>
      <inputMethod>button</inputMethod>
      <fieldType>INPUT</fieldType>
      <required>false</required>
      <unit></unit>
      <prefix></prefix>
      <suffix></suffix>
      <param></param>
      <dataSource></dataSource>
    </TFieldDef>

    <TFieldDef>
      <pageNo>2</pageNo>
      <id>headerButtons</id>
      <groupType>buttons</groupType>
      <columnCount>0</columnCount>
      <labelStyle></labelStyle>
      <outerStyle></outerStyle>
      <innerStyle>rightButtons</innerStyle>
      <inputMethod></inputMethod>
      <fieldType>NOLABELOUTPUT</fieldType>
      <required>false</required>
      <unit></unit>
      <prefix></prefix>
      <suffix></suffix>
      <param></param>
      <dataSource></dataSource>
    </TFieldDef>
    <TFieldDef>
      <pageNo>2</pageNo>
      <id>headerButtons:tojiruBtn</id>
      <format></format>
      <groupType></groupType>
      <columnCount>0</columnCount>
      <labelStyle></labelStyle>
      <outerStyle></outerStyle>
      <innerStyle></innerStyle>
      <inputMethod>closeButton</inputMethod>
      <fieldType>INPUT</fieldType>
      <required>false</required>
      <unit></unit>
      <prefix></prefix>
      <suffix></suffix>
      <param></param>
      <dataSource></dataSource>
    </TFieldDef>
    <TFieldDef>
      <pageNo>2</pageNo>
      <id>kihonInfo</id>
      <groupType>group</groupType>
      <columnCount>1</columnCount>
      <labelStyle></labelStyle>
      <outerStyle></outerStyle>
      <innerStyle></innerStyle>
      <inputMethod></inputMethod>
      <fieldType>NOLABELOUTPUT</fieldType>
      <required>false</required>
      <unit></unit>
      <prefix></prefix>
      <suffix></suffix>
      <param></param>
      <dataSource></dataSource>
    </TFieldDef>
    <TFieldDef>
      <pageNo>2</pageNo>
      <id>kihonInfo:syono</id>
      <format></format>
      <groupType></groupType>
      <columnCount>1</columnCount>
      <labelStyle></labelStyle>
      <outerStyle>c1</outerStyle>
      <innerStyle></innerStyle>
      <inputMethod>text</inputMethod>
      <fieldType>OUTPUT</fieldType>
      <required>false</required>
      <unit></unit>
      <prefix></prefix>
      <suffix></suffix>
      <param></param>
      <dataSource></dataSource>
    </TFieldDef>
    <TFieldDef>
      <pageNo>2</pageNo>
      <id>kihonInfo:skno</id>
      <format></format>
      <groupType></groupType>
      <columnCount>1</columnCount>
      <labelStyle></labelStyle>
      <outerStyle>c1</outerStyle>
      <innerStyle></innerStyle>
      <inputMethod>text</inputMethod>
      <fieldType>OUTPUT</fieldType>
      <required>false</required>
      <unit></unit>
      <prefix></prefix>
      <suffix></suffix>
      <param></param>
      <dataSource></dataSource>
    </TFieldDef>
    <TFieldDef>
      <pageNo>2</pageNo>
      <id>keiyakusyaInfo</id>
      <groupType>group</groupType>
      <columnCount>2</columnCount>
      <labelStyle></labelStyle>
      <outerStyle></outerStyle>
      <innerStyle></innerStyle>
      <inputMethod></inputMethod>
      <fieldType>OUTPUT</fieldType>
      <required>false</required>
      <unit></unit>
      <prefix></prefix>
      <suffix></suffix>
      <param></param>
      <dataSource></dataSource>
    </TFieldDef>
    <TFieldDef>
      <pageNo>2</pageNo>
      <id>keiyakusyaInfo:kyknmkn</id>
      <format></format>
      <groupType></groupType>
      <columnCount>2</columnCount>
      <labelStyle></labelStyle>
      <outerStyle>c1</outerStyle>
      <innerStyle></innerStyle>
      <inputMethod>text</inputMethod>
      <fieldType>OUTPUT</fieldType>
      <required>false</required>
      <unit></unit>
      <prefix></prefix>
      <suffix></suffix>
      <param></param>
      <dataSource></dataSource>
    </TFieldDef>
    <TFieldDef>
      <pageNo>2</pageNo>
      <id>keiyakusyaInfo:kyknmkj</id>
      <format></format>
      <groupType></groupType>
      <columnCount>2</columnCount>
      <labelStyle></labelStyle>
      <outerStyle>c1</outerStyle>
      <innerStyle></innerStyle>
      <inputMethod>text</inputMethod>
      <fieldType>OUTPUT</fieldType>
      <required>false</required>
      <unit></unit>
      <prefix></prefix>
      <suffix></suffix>
      <param></param>
      <dataSource></dataSource>
    </TFieldDef>
    <TFieldDef>
      <pageNo>2</pageNo>
      <id>keiyakusyaInfo:kykseiymd</id>
      <format></format>
      <groupType></groupType>
      <columnCount>1</columnCount>
      <labelStyle></labelStyle>
      <outerStyle>c2</outerStyle>
      <innerStyle></innerStyle>
      <inputMethod>dateYMD_WAREKI_SYMBOL</inputMethod>
      <fieldType>OUTPUT</fieldType>
      <required>false</required>
      <unit></unit>
      <prefix></prefix>
      <suffix></suffix>
      <param>birthday</param>
      <dataSource></dataSource>
    </TFieldDef>
    <TFieldDef>
      <pageNo>2</pageNo>
      <id>keiyakusyaInfo:kyksei</id>
      <format></format>
      <groupType></groupType>
      <columnCount>1</columnCount>
      <labelStyle></labelStyle>
      <outerStyle>c2</outerStyle>
      <innerStyle></innerStyle>
      <inputMethod>select</inputMethod>
      <fieldType>OUTPUT</fieldType>
      <required>false</required>
      <unit></unit>
      <prefix></prefix>
      <suffix></suffix>
      <param></param>
      <dataSource></dataSource>
      <kbnPattern>1</kbnPattern>
    </TFieldDef>
    <TFieldDef>
      <pageNo>2</pageNo>
      <id>hihokensyaInfo</id>
      <groupType>group</groupType>
      <columnCount>2</columnCount>
      <labelStyle></labelStyle>
      <outerStyle></outerStyle>
      <innerStyle></innerStyle>
      <inputMethod></inputMethod>
      <fieldType>OUTPUT</fieldType>
      <required>false</required>
      <unit></unit>
      <prefix></prefix>
      <suffix></suffix>
      <param></param>
      <dataSource></dataSource>
    </TFieldDef>
    <TFieldDef>
      <pageNo>2</pageNo>
      <id>hihokensyaInfo:hhknnmkn</id>
      <format></format>
      <groupType></groupType>
      <columnCount>2</columnCount>
      <labelStyle></labelStyle>
      <outerStyle>c1</outerStyle>
      <innerStyle></innerStyle>
      <inputMethod>text</inputMethod>
      <fieldType>OUTPUT</fieldType>
      <required>false</required>
      <unit></unit>
      <prefix></prefix>
      <suffix></suffix>
      <param></param>
      <dataSource></dataSource>
    </TFieldDef>
    <TFieldDef>
      <pageNo>2</pageNo>
      <id>hihokensyaInfo:hhknnmkj</id>
      <format></format>
      <groupType></groupType>
      <columnCount>2</columnCount>
      <labelStyle></labelStyle>
      <outerStyle>c1</outerStyle>
      <innerStyle></innerStyle>
      <inputMethod>text</inputMethod>
      <fieldType>OUTPUT</fieldType>
      <required>false</required>
      <unit></unit>
      <prefix></prefix>
      <suffix></suffix>
      <param></param>
      <dataSource></dataSource>
    </TFieldDef>
    <TFieldDef>
      <pageNo>2</pageNo>
      <id>hihokensyaInfo:hhknseiymd</id>
      <format></format>
      <groupType></groupType>
      <columnCount>1</columnCount>
      <labelStyle></labelStyle>
      <outerStyle>c2</outerStyle>
      <innerStyle></innerStyle>
      <inputMethod>dateYMD_WAREKI_SYMBOL</inputMethod>
      <fieldType>OUTPUT</fieldType>
      <required>false</required>
      <unit></unit>
      <prefix></prefix>
      <suffix></suffix>
      <param>birthday</param>
      <dataSource></dataSource>
    </TFieldDef>
    <TFieldDef>
      <pageNo>2</pageNo>
      <id>hihokensyaInfo:hhknsei</id>
      <format></format>
      <groupType></groupType>
      <columnCount>1</columnCount>
      <labelStyle></labelStyle>
      <outerStyle>c2</outerStyle>
      <innerStyle></innerStyle>
      <inputMethod>select</inputMethod>
      <fieldType>OUTPUT</fieldType>
      <required>false</required>
      <unit></unit>
      <prefix></prefix>
      <suffix></suffix>
      <param></param>
      <dataSource></dataSource>
      <kbnPattern>1</kbnPattern>
    </TFieldDef>
    <TFieldDef>
      <pageNo>2</pageNo>
      <id>bikouInfoBefore</id>
      <groupType>group</groupType>
      <columnCount>1</columnCount>
      <labelStyle></labelStyle>
      <outerStyle></outerStyle>
      <innerStyle></innerStyle>
      <inputMethod></inputMethod>
      <fieldType>OUTPUT</fieldType>
      <required>false</required>
      <unit></unit>
      <prefix></prefix>
      <suffix></suffix>
      <param></param>
      <dataSource></dataSource>
    </TFieldDef>
    <TFieldDef>
      <pageNo>2</pageNo>
      <id>bikouInfoBefore:siboukaritrkymd</id>
      <format></format>
      <groupType></groupType>
      <columnCount>1</columnCount>
      <labelStyle></labelStyle>
      <outerStyle>c1</outerStyle>
      <innerStyle></innerStyle>
      <inputMethod>dateYMD</inputMethod>
      <fieldType>OUTPUT</fieldType>
      <required>false</required>
      <unit></unit>
      <prefix></prefix>
      <suffix></suffix>
      <param></param>
      <dataSource></dataSource>
    </TFieldDef>
    <TFieldDef>
      <pageNo>2</pageNo>
      <id>bikouInfoAfter</id>
      <groupType>group</groupType>
      <columnCount>1</columnCount>
      <labelStyle></labelStyle>
      <outerStyle></outerStyle>
      <innerStyle></innerStyle>
      <inputMethod></inputMethod>
      <fieldType>OUTPUT</fieldType>
      <required>false</required>
      <unit></unit>
      <prefix></prefix>
      <suffix></suffix>
      <param></param>
      <dataSource></dataSource>
    </TFieldDef>
    <TFieldDef>
      <pageNo>2</pageNo>
      <id>bikouInfoAfter:bknkktymd</id>
      <format></format>
      <groupType></groupType>
      <columnCount>1</columnCount>
      <labelStyle></labelStyle>
      <outerStyle>c1</outerStyle>
      <innerStyle></innerStyle>
      <inputMethod>dateYMD</inputMethod>
      <fieldType>INPUT</fieldType>
      <required>true</required>
      <unit></unit>
      <prefix></prefix>
      <suffix></suffix>
      <param></param>
      <dataSource></dataSource>
    </TFieldDef>
    <TFieldDef>
      <pageNo>2</pageNo>
      <id>footerButtons</id>
      <groupType>buttons</groupType>
      <columnCount>1</columnCount>
      <labelStyle></labelStyle>
      <outerStyle></outerStyle>
      <innerStyle></innerStyle>
      <inputMethod></inputMethod>
      <fieldType>NOLABELOUTPUT</fieldType>
      <required>false</required>
      <unit></unit>
      <prefix></prefix>
      <suffix></suffix>
      <param></param>
      <dataSource></dataSource>
    </TFieldDef>
    <TFieldDef>
      <pageNo>2</pageNo>
      <id>footerButtons:modoruBtnByInputContents</id>
      <format></format>
      <groupType></groupType>
      <columnCount>1</columnCount>
      <labelStyle></labelStyle>
      <outerStyle></outerStyle>
      <innerStyle></innerStyle>
      <inputMethod>noValidationButton</inputMethod>
      <fieldType>INPUT</fieldType>
      <required>false</required>
      <unit></unit>
      <prefix></prefix>
      <suffix></suffix>
      <param></param>
      <dataSource></dataSource>
    </TFieldDef>
    <TFieldDef>
      <pageNo>2</pageNo>
      <id>footerButtons:kakuninBtn</id>
      <format></format>
      <groupType></groupType>
      <columnCount>1</columnCount>
      <labelStyle></labelStyle>
      <outerStyle></outerStyle>
      <innerStyle></innerStyle>
      <inputMethod>button</inputMethod>
      <fieldType>INPUT</fieldType>
      <required>false</required>
      <unit></unit>
      <prefix></prefix>
      <suffix></suffix>
      <param></param>
      <dataSource></dataSource>
    </TFieldDef>

    <TFieldDef>
      <pageNo>3</pageNo>
      <id>headerButtons</id>
      <groupType>buttons</groupType>
      <columnCount>0</columnCount>
      <labelStyle></labelStyle>
      <outerStyle></outerStyle>
      <innerStyle>rightButtons</innerStyle>
      <inputMethod></inputMethod>
      <fieldType>NOLABELOUTPUT</fieldType>
      <required>false</required>
      <unit></unit>
      <prefix></prefix>
      <suffix></suffix>
      <param></param>
      <dataSource></dataSource>
    </TFieldDef>
    <TFieldDef>
      <pageNo>3</pageNo>
      <id>headerButtons:tojiruBtn</id>
      <format></format>
      <groupType></groupType>
      <columnCount>0</columnCount>
      <labelStyle></labelStyle>
      <outerStyle></outerStyle>
      <innerStyle></innerStyle>
      <inputMethod>closeButton</inputMethod>
      <fieldType>INPUT</fieldType>
      <required>false</required>
      <unit></unit>
      <prefix></prefix>
      <suffix></suffix>
      <param></param>
      <dataSource></dataSource>
    </TFieldDef>
    <TFieldDef>
      <pageNo>3</pageNo>
      <id>kihonInfo</id>
      <groupType>group</groupType>
      <columnCount>1</columnCount>
      <labelStyle></labelStyle>
      <outerStyle></outerStyle>
      <innerStyle></innerStyle>
      <inputMethod></inputMethod>
      <fieldType>NOLABELOUTPUT</fieldType>
      <required>false</required>
      <unit></unit>
      <prefix></prefix>
      <suffix></suffix>
      <param></param>
      <dataSource></dataSource>
    </TFieldDef>
    <TFieldDef>
      <pageNo>3</pageNo>
      <id>kihonInfo:syono</id>
      <format></format>
      <groupType></groupType>
      <columnCount>1</columnCount>
      <labelStyle></labelStyle>
      <outerStyle>c1</outerStyle>
      <innerStyle></innerStyle>
      <inputMethod>text</inputMethod>
      <fieldType>OUTPUT</fieldType>
      <required>false</required>
      <unit></unit>
      <prefix></prefix>
      <suffix></suffix>
      <param></param>
      <dataSource></dataSource>
    </TFieldDef>
    <TFieldDef>
      <pageNo>3</pageNo>
      <id>kihonInfo:skno</id>
      <format></format>
      <groupType></groupType>
      <columnCount>1</columnCount>
      <labelStyle></labelStyle>
      <outerStyle>c1</outerStyle>
      <innerStyle></innerStyle>
      <inputMethod>text</inputMethod>
      <fieldType>OUTPUT</fieldType>
      <required>false</required>
      <unit></unit>
      <prefix></prefix>
      <suffix></suffix>
      <param></param>
      <dataSource></dataSource>
    </TFieldDef>
    <TFieldDef>
      <pageNo>3</pageNo>
      <id>keiyakusyaInfo</id>
      <groupType>group</groupType>
      <columnCount>2</columnCount>
      <labelStyle></labelStyle>
      <outerStyle></outerStyle>
      <innerStyle></innerStyle>
      <inputMethod></inputMethod>
      <fieldType>OUTPUT</fieldType>
      <required>false</required>
      <unit></unit>
      <prefix></prefix>
      <suffix></suffix>
      <param></param>
      <dataSource></dataSource>
    </TFieldDef>
    <TFieldDef>
      <pageNo>3</pageNo>
      <id>keiyakusyaInfo:kyknmkn</id>
      <format></format>
      <groupType></groupType>
      <columnCount>2</columnCount>
      <labelStyle></labelStyle>
      <outerStyle>c1</outerStyle>
      <innerStyle></innerStyle>
      <inputMethod>text</inputMethod>
      <fieldType>OUTPUT</fieldType>
      <required>false</required>
      <unit></unit>
      <prefix></prefix>
      <suffix></suffix>
      <param></param>
      <dataSource></dataSource>
    </TFieldDef>
    <TFieldDef>
      <pageNo>3</pageNo>
      <id>keiyakusyaInfo:kyknmkj</id>
      <format></format>
      <groupType></groupType>
      <columnCount>2</columnCount>
      <labelStyle></labelStyle>
      <outerStyle>c1</outerStyle>
      <innerStyle></innerStyle>
      <inputMethod>text</inputMethod>
      <fieldType>OUTPUT</fieldType>
      <required>false</required>
      <unit></unit>
      <prefix></prefix>
      <suffix></suffix>
      <param></param>
      <dataSource></dataSource>
    </TFieldDef>
    <TFieldDef>
      <pageNo>3</pageNo>
      <id>keiyakusyaInfo:kykseiymd</id>
      <format></format>
      <groupType></groupType>
      <columnCount>1</columnCount>
      <labelStyle></labelStyle>
      <outerStyle>c2</outerStyle>
      <innerStyle></innerStyle>
      <inputMethod>dateYMD_WAREKI_SYMBOL</inputMethod>
      <fieldType>OUTPUT</fieldType>
      <required>false</required>
      <unit></unit>
      <prefix></prefix>
      <suffix></suffix>
      <param>birthday</param>
      <dataSource></dataSource>
    </TFieldDef>
    <TFieldDef>
      <pageNo>3</pageNo>
      <id>keiyakusyaInfo:kyksei</id>
      <format></format>
      <groupType></groupType>
      <columnCount>1</columnCount>
      <labelStyle></labelStyle>
      <outerStyle>c2</outerStyle>
      <innerStyle></innerStyle>
      <inputMethod>select</inputMethod>
      <fieldType>OUTPUT</fieldType>
      <required>false</required>
      <unit></unit>
      <prefix></prefix>
      <suffix></suffix>
      <param></param>
      <dataSource></dataSource>
      <kbnPattern>1</kbnPattern>
    </TFieldDef>
    <TFieldDef>
      <pageNo>3</pageNo>
      <id>hihokensyaInfo</id>
      <groupType>group</groupType>
      <columnCount>2</columnCount>
      <labelStyle></labelStyle>
      <outerStyle></outerStyle>
      <innerStyle></innerStyle>
      <inputMethod></inputMethod>
      <fieldType>OUTPUT</fieldType>
      <required>false</required>
      <unit></unit>
      <prefix></prefix>
      <suffix></suffix>
      <param></param>
      <dataSource></dataSource>
    </TFieldDef>
    <TFieldDef>
      <pageNo>3</pageNo>
      <id>hihokensyaInfo:hhknnmkn</id>
      <format></format>
      <groupType></groupType>
      <columnCount>2</columnCount>
      <labelStyle></labelStyle>
      <outerStyle>c1</outerStyle>
      <innerStyle></innerStyle>
      <inputMethod>text</inputMethod>
      <fieldType>OUTPUT</fieldType>
      <required>false</required>
      <unit></unit>
      <prefix></prefix>
      <suffix></suffix>
      <param></param>
      <dataSource></dataSource>
    </TFieldDef>
    <TFieldDef>
      <pageNo>3</pageNo>
      <id>hihokensyaInfo:hhknnmkj</id>
      <format></format>
      <groupType></groupType>
      <columnCount>2</columnCount>
      <labelStyle></labelStyle>
      <outerStyle>c1</outerStyle>
      <innerStyle></innerStyle>
      <inputMethod>text</inputMethod>
      <fieldType>OUTPUT</fieldType>
      <required>false</required>
      <unit></unit>
      <prefix></prefix>
      <suffix></suffix>
      <param></param>
      <dataSource></dataSource>
    </TFieldDef>
    <TFieldDef>
      <pageNo>3</pageNo>
      <id>hihokensyaInfo:hhknseiymd</id>
      <format></format>
      <groupType></groupType>
      <columnCount>1</columnCount>
      <labelStyle></labelStyle>
      <outerStyle>c2</outerStyle>
      <innerStyle></innerStyle>
      <inputMethod>dateYMD_WAREKI_SYMBOL</inputMethod>
      <fieldType>OUTPUT</fieldType>
      <required>false</required>
      <unit></unit>
      <prefix></prefix>
      <suffix></suffix>
      <param>birthday</param>
      <dataSource></dataSource>
    </TFieldDef>
    <TFieldDef>
      <pageNo>3</pageNo>
      <id>hihokensyaInfo:hhknsei</id>
      <format></format>
      <groupType></groupType>
      <columnCount>1</columnCount>
      <labelStyle></labelStyle>
      <outerStyle>c2</outerStyle>
      <innerStyle></innerStyle>
      <inputMethod>select</inputMethod>
      <fieldType>OUTPUT</fieldType>
      <required>false</required>
      <unit></unit>
      <prefix></prefix>
      <suffix></suffix>
      <param></param>
      <dataSource></dataSource>
      <kbnPattern>1</kbnPattern>
    </TFieldDef>
    <TFieldDef>
      <pageNo>3</pageNo>
      <id>bikouInfoBefore</id>
      <groupType>group</groupType>
      <columnCount>1</columnCount>
      <labelStyle></labelStyle>
      <outerStyle></outerStyle>
      <innerStyle></innerStyle>
      <inputMethod></inputMethod>
      <fieldType>OUTPUT</fieldType>
      <required>false</required>
      <unit></unit>
      <prefix></prefix>
      <suffix></suffix>
      <param></param>
      <dataSource></dataSource>
    </TFieldDef>
    <TFieldDef>
      <pageNo>3</pageNo>
      <id>bikouInfoBefore:siboukaritrkymd</id>
      <format></format>
      <groupType></groupType>
      <columnCount>1</columnCount>
      <labelStyle></labelStyle>
      <outerStyle>c1</outerStyle>
      <innerStyle></innerStyle>
      <inputMethod>dateYMD</inputMethod>
      <fieldType>OUTPUT</fieldType>
      <required>false</required>
      <unit></unit>
      <prefix></prefix>
      <suffix></suffix>
      <param></param>
      <dataSource></dataSource>
    </TFieldDef>
    <TFieldDef>
      <pageNo>3</pageNo>
      <id>bikouInfoAfter</id>
      <groupType>group</groupType>
      <columnCount>1</columnCount>
      <labelStyle></labelStyle>
      <outerStyle></outerStyle>
      <innerStyle></innerStyle>
      <inputMethod></inputMethod>
      <fieldType>OUTPUT</fieldType>
      <required>false</required>
      <unit></unit>
      <prefix></prefix>
      <suffix></suffix>
      <param></param>
      <dataSource></dataSource>
    </TFieldDef>
    <TFieldDef>
      <pageNo>3</pageNo>
      <id>bikouInfoAfter:bknkktymd</id>
      <format></format>
      <groupType></groupType>
      <columnCount>1</columnCount>
      <labelStyle></labelStyle>
      <outerStyle>c1</outerStyle>
      <innerStyle></innerStyle>
      <inputMethod>dateYMD</inputMethod>
      <fieldType>OUTPUT</fieldType>
      <required>false</required>
      <unit></unit>
      <prefix></prefix>
      <suffix></suffix>
      <param></param>
      <dataSource></dataSource>
    </TFieldDef>
    <TFieldDef>
      <pageNo>3</pageNo>
      <id>footerButtons</id>
      <groupType>buttons</groupType>
      <columnCount>1</columnCount>
      <labelStyle></labelStyle>
      <outerStyle></outerStyle>
      <innerStyle></innerStyle>
      <inputMethod></inputMethod>
      <fieldType>NOLABELOUTPUT</fieldType>
      <required>false</required>
      <unit></unit>
      <prefix></prefix>
      <suffix></suffix>
      <param></param>
      <dataSource></dataSource>
    </TFieldDef>
    <TFieldDef>
      <pageNo>3</pageNo>
      <id>footerButtons:modoruBtnByConfirm</id>
      <format></format>
      <groupType></groupType>
      <columnCount>1</columnCount>
      <labelStyle></labelStyle>
      <outerStyle></outerStyle>
      <innerStyle></innerStyle>
      <inputMethod>noValidationButton</inputMethod>
      <fieldType>INPUT</fieldType>
      <required>false</required>
      <unit></unit>
      <prefix></prefix>
      <suffix></suffix>
      <param></param>
      <dataSource></dataSource>
    </TFieldDef>
    <TFieldDef>
      <pageNo>3</pageNo>
      <id>footerButtons:kakuteiBtn</id>
      <format></format>
      <groupType></groupType>
      <columnCount>1</columnCount>
      <labelStyle></labelStyle>
      <outerStyle></outerStyle>
      <innerStyle></innerStyle>
      <inputMethod>noValidationButton</inputMethod>
      <fieldType>INPUT</fieldType>
      <required>false</required>
      <unit></unit>
      <prefix></prefix>
      <suffix></suffix>
      <param></param>
      <dataSource></dataSource>
    </TFieldDef>

    <TFieldDef>
      <pageNo>4</pageNo>
      <id>headerButtons</id>
      <groupType>buttons</groupType>
      <columnCount>0</columnCount>
      <labelStyle></labelStyle>
      <outerStyle></outerStyle>
      <innerStyle>rightButtons</innerStyle>
      <inputMethod></inputMethod>
      <fieldType>NOLABELOUTPUT</fieldType>
      <required>false</required>
      <unit></unit>
      <prefix></prefix>
      <suffix></suffix>
      <param></param>
      <dataSource></dataSource>
    </TFieldDef>
    <TFieldDef>
      <pageNo>4</pageNo>
      <id>headerButtons:tojiruBtn</id>
      <format></format>
      <groupType></groupType>
      <columnCount>0</columnCount>
      <labelStyle></labelStyle>
      <outerStyle></outerStyle>
      <innerStyle></innerStyle>
      <inputMethod>closeButton</inputMethod>
      <fieldType>INPUT</fieldType>
      <required>false</required>
      <unit></unit>
      <prefix></prefix>
      <suffix></suffix>
      <param></param>
      <dataSource></dataSource>
    </TFieldDef>
    <TFieldDef>
      <pageNo>4</pageNo>
      <id>kihonInfo</id>
      <groupType>group</groupType>
      <columnCount>1</columnCount>
      <labelStyle></labelStyle>
      <outerStyle></outerStyle>
      <innerStyle></innerStyle>
      <inputMethod></inputMethod>
      <fieldType>NOLABELOUTPUT</fieldType>
      <required>false</required>
      <unit></unit>
      <prefix></prefix>
      <suffix></suffix>
      <param></param>
      <dataSource></dataSource>
    </TFieldDef>
    <TFieldDef>
      <pageNo>4</pageNo>
      <id>kihonInfo:syono</id>
      <format></format>
      <groupType></groupType>
      <columnCount>1</columnCount>
      <labelStyle></labelStyle>
      <outerStyle>c1</outerStyle>
      <innerStyle></innerStyle>
      <inputMethod>text</inputMethod>
      <fieldType>OUTPUT</fieldType>
      <required>false</required>
      <unit></unit>
      <prefix></prefix>
      <suffix></suffix>
      <param></param>
      <dataSource></dataSource>
    </TFieldDef>
    <TFieldDef>
      <pageNo>4</pageNo>
      <id>kihonInfo:skno</id>
      <format></format>
      <groupType></groupType>
      <columnCount>1</columnCount>
      <labelStyle></labelStyle>
      <outerStyle>c1</outerStyle>
      <innerStyle></innerStyle>
      <inputMethod>text</inputMethod>
      <fieldType>OUTPUT</fieldType>
      <required>false</required>
      <unit></unit>
      <prefix></prefix>
      <suffix></suffix>
      <param></param>
      <dataSource></dataSource>
    </TFieldDef>
    <TFieldDef>
      <pageNo>4</pageNo>
      <id>keiyakusyaInfo</id>
      <groupType>group</groupType>
      <columnCount>2</columnCount>
      <labelStyle></labelStyle>
      <outerStyle></outerStyle>
      <innerStyle></innerStyle>
      <inputMethod></inputMethod>
      <fieldType>OUTPUT</fieldType>
      <required>false</required>
      <unit></unit>
      <prefix></prefix>
      <suffix></suffix>
      <param></param>
      <dataSource></dataSource>
    </TFieldDef>
    <TFieldDef>
      <pageNo>4</pageNo>
      <id>keiyakusyaInfo:kyknmkn</id>
      <format></format>
      <groupType></groupType>
      <columnCount>2</columnCount>
      <labelStyle></labelStyle>
      <outerStyle>c1</outerStyle>
      <innerStyle></innerStyle>
      <inputMethod>text</inputMethod>
      <fieldType>OUTPUT</fieldType>
      <required>false</required>
      <unit></unit>
      <prefix></prefix>
      <suffix></suffix>
      <param></param>
      <dataSource></dataSource>
    </TFieldDef>
    <TFieldDef>
      <pageNo>4</pageNo>
      <id>keiyakusyaInfo:kyknmkj</id>
      <format></format>
      <groupType></groupType>
      <columnCount>2</columnCount>
      <labelStyle></labelStyle>
      <outerStyle>c1</outerStyle>
      <innerStyle></innerStyle>
      <inputMethod>text</inputMethod>
      <fieldType>OUTPUT</fieldType>
      <required>false</required>
      <unit></unit>
      <prefix></prefix>
      <suffix></suffix>
      <param></param>
      <dataSource></dataSource>
    </TFieldDef>
    <TFieldDef>
      <pageNo>4</pageNo>
      <id>keiyakusyaInfo:kykseiymd</id>
      <format></format>
      <groupType></groupType>
      <columnCount>1</columnCount>
      <labelStyle></labelStyle>
      <outerStyle>c2</outerStyle>
      <innerStyle></innerStyle>
      <inputMethod>dateYMD_WAREKI_SYMBOL</inputMethod>
      <fieldType>OUTPUT</fieldType>
      <required>false</required>
      <unit></unit>
      <prefix></prefix>
      <suffix></suffix>
      <param>birthday</param>
      <dataSource></dataSource>
    </TFieldDef>
    <TFieldDef>
      <pageNo>4</pageNo>
      <id>keiyakusyaInfo:kyksei</id>
      <format></format>
      <groupType></groupType>
      <columnCount>1</columnCount>
      <labelStyle></labelStyle>
      <outerStyle>c2</outerStyle>
      <innerStyle></innerStyle>
      <inputMethod>select</inputMethod>
      <fieldType>OUTPUT</fieldType>
      <required>false</required>
      <unit></unit>
      <prefix></prefix>
      <suffix></suffix>
      <param></param>
      <dataSource></dataSource>
      <kbnPattern>1</kbnPattern>
    </TFieldDef>
    <TFieldDef>
      <pageNo>4</pageNo>
      <id>hihokensyaInfo</id>
      <groupType>group</groupType>
      <columnCount>2</columnCount>
      <labelStyle></labelStyle>
      <outerStyle></outerStyle>
      <innerStyle></innerStyle>
      <inputMethod></inputMethod>
      <fieldType>OUTPUT</fieldType>
      <required>false</required>
      <unit></unit>
      <prefix></prefix>
      <suffix></suffix>
      <param></param>
      <dataSource></dataSource>
    </TFieldDef>
    <TFieldDef>
      <pageNo>4</pageNo>
      <id>hihokensyaInfo:hhknnmkn</id>
      <format></format>
      <groupType></groupType>
      <columnCount>2</columnCount>
      <labelStyle></labelStyle>
      <outerStyle>c1</outerStyle>
      <innerStyle></innerStyle>
      <inputMethod>text</inputMethod>
      <fieldType>OUTPUT</fieldType>
      <required>false</required>
      <unit></unit>
      <prefix></prefix>
      <suffix></suffix>
      <param></param>
      <dataSource></dataSource>
    </TFieldDef>
    <TFieldDef>
      <pageNo>4</pageNo>
      <id>hihokensyaInfo:hhknnmkj</id>
      <format></format>
      <groupType></groupType>
      <columnCount>2</columnCount>
      <labelStyle></labelStyle>
      <outerStyle>c1</outerStyle>
      <innerStyle></innerStyle>
      <inputMethod>text</inputMethod>
      <fieldType>OUTPUT</fieldType>
      <required>false</required>
      <unit></unit>
      <prefix></prefix>
      <suffix></suffix>
      <param></param>
      <dataSource></dataSource>
    </TFieldDef>
    <TFieldDef>
      <pageNo>4</pageNo>
      <id>hihokensyaInfo:hhknseiymd</id>
      <format></format>
      <groupType></groupType>
      <columnCount>1</columnCount>
      <labelStyle></labelStyle>
      <outerStyle>c2</outerStyle>
      <innerStyle></innerStyle>
      <inputMethod>dateYMD_WAREKI_SYMBOL</inputMethod>
      <fieldType>OUTPUT</fieldType>
      <required>false</required>
      <unit></unit>
      <prefix></prefix>
      <suffix></suffix>
      <param>birthday</param>
      <dataSource></dataSource>
    </TFieldDef>
    <TFieldDef>
      <pageNo>4</pageNo>
      <id>hihokensyaInfo:hhknsei</id>
      <format></format>
      <groupType></groupType>
      <columnCount>1</columnCount>
      <labelStyle></labelStyle>
      <outerStyle>c2</outerStyle>
      <innerStyle></innerStyle>
      <inputMethod>select</inputMethod>
      <fieldType>OUTPUT</fieldType>
      <required>false</required>
      <unit></unit>
      <prefix></prefix>
      <suffix></suffix>
      <param></param>
      <dataSource></dataSource>
      <kbnPattern>1</kbnPattern>
    </TFieldDef>
    <TFieldDef>
      <pageNo>4</pageNo>
      <id>bikouInfoBefore</id>
      <groupType>group</groupType>
      <columnCount>1</columnCount>
      <labelStyle></labelStyle>
      <outerStyle></outerStyle>
      <innerStyle></innerStyle>
      <inputMethod></inputMethod>
      <fieldType>OUTPUT</fieldType>
      <required>false</required>
      <unit></unit>
      <prefix></prefix>
      <suffix></suffix>
      <param></param>
      <dataSource></dataSource>
    </TFieldDef>
    <TFieldDef>
      <pageNo>4</pageNo>
      <id>bikouInfoBefore:siboukaritrkymd</id>
      <format></format>
      <groupType></groupType>
      <columnCount>1</columnCount>
      <labelStyle></labelStyle>
      <outerStyle>c1</outerStyle>
      <innerStyle></innerStyle>
      <inputMethod>dateYMD</inputMethod>
      <fieldType>OUTPUT</fieldType>
      <required>false</required>
      <unit></unit>
      <prefix></prefix>
      <suffix></suffix>
      <param></param>
      <dataSource></dataSource>
    </TFieldDef>
    <TFieldDef>
      <pageNo>4</pageNo>
      <id>bikouInfoAfter</id>
      <groupType>group</groupType>
      <columnCount>1</columnCount>
      <labelStyle></labelStyle>
      <outerStyle></outerStyle>
      <innerStyle></innerStyle>
      <inputMethod></inputMethod>
      <fieldType>OUTPUT</fieldType>
      <required>false</required>
      <unit></unit>
      <prefix></prefix>
      <suffix></suffix>
      <param></param>
      <dataSource></dataSource>
    </TFieldDef>
    <TFieldDef>
      <pageNo>4</pageNo>
      <id>bikouInfoAfter:bknkktymd</id>
      <format></format>
      <groupType></groupType>
      <columnCount>1</columnCount>
      <labelStyle></labelStyle>
      <outerStyle>c1</outerStyle>
      <innerStyle></innerStyle>
      <inputMethod>dateYMD</inputMethod>
      <fieldType>OUTPUT</fieldType>
      <required>false</required>
      <unit></unit>
      <prefix></prefix>
      <suffix></suffix>
      <param></param>
      <dataSource></dataSource>
    </TFieldDef>
    <TFieldDef>
      <pageNo>4</pageNo>
      <id>footerButtons</id>
      <groupType>buttons</groupType>
      <columnCount>1</columnCount>
      <labelStyle></labelStyle>
      <outerStyle></outerStyle>
      <innerStyle></innerStyle>
      <inputMethod></inputMethod>
      <fieldType>NOLABELOUTPUT</fieldType>
      <required>false</required>
      <unit></unit>
      <prefix></prefix>
      <suffix></suffix>
      <param></param>
      <dataSource></dataSource>
    </TFieldDef>
    <TFieldDef>
      <pageNo>4</pageNo>
      <id>footerButtons:syokigamenheBtn</id>
      <format></format>
      <groupType></groupType>
      <columnCount>1</columnCount>
      <labelStyle></labelStyle>
      <outerStyle></outerStyle>
      <innerStyle></innerStyle>
      <inputMethod>noValidationButton</inputMethod>
      <fieldType>INPUT</fieldType>
      <required>false</required>
      <unit></unit>
      <prefix></prefix>
      <suffix></suffix>
      <param></param>
      <dataSource></dataSource>
    </TFieldDef>
  </TFieldDefs>
</kinouDef>
